pine_client/__init__.py
pine_client/client.py
pine_client/utils.py
pine_client-0.1.3.dist-info/METADATA
pine_client-0.1.3.dist-info/WHEEL
pine_client-0.1.3.dist-info/RECORD
